AUTHORS.rst
HISTORY.rst
LICENSE
MANIFEST.in
README.rst
setup.cfg
setup.py
sss_auth.egg-info/PKG-INFO
sss_auth.egg-info/SOURCES.txt
sss_auth.egg-info/dependency_links.txt
sss_auth.egg-info/not-zip-safe
sss_auth.egg-info/requires.txt
sss_auth.egg-info/top_level.txt
sssauth/__init__.py
sssauth/apps.py
sssauth/backend.py
sssauth/forms.py
sssauth/models.py
sssauth/settings.py
sssauth/urls.py
sssauth/utils.py
sssauth/views.py
sssauth/wsgi.py
sssauth/migrations/0001_initial.py
sssauth/migrations/0002_alter_myuser_email_alter_myuser_username.py
sssauth/migrations/0003_alter_myuser_username.py
sssauth/migrations/0004_alter_myuser_username.py
sssauth/migrations/0005_alter_myuser_username.py
sssauth/migrations/__init__.py
sssauth/static/sssauth/css/web3auth.css
sssauth/static/sssauth/js/sssAuth.js
sssauth/templates/web3auth/base.html
sssauth/templates/web3auth/signup.html