Metadata-Version: 2.1
Name: sss-auth
Version: 0.0.2
Summary: sssauth is a pluggable Django app that enables login/signup via an SSS Extension
Home-page: https://github.com/SafelySignSymbol/django-sss-auth-boilerplate
Author: SSS-Extension
Author-email: notify.monakaxym@bgmail.com
License: MIT
Keywords: sssauth
Platform: UNKNOWN
Classifier: Framework :: Django :: 4.0
Classifier: Intended Audience :: Developers
Classifier: License :: OSI Approved :: MIT License
Classifier: Natural Language :: Japanese
License-File: LICENSE
License-File: AUTHORS.rst
